nmdown/__init__.py
nmdown/cli.py
nmdown-0.1.0.dist-info/METADATA
nmdown-0.1.0.dist-info/WHEEL
nmdown-0.1.0.dist-info/entry_points.txt
nmdown-0.1.0.dist-info/top_level.txt
nmdown-0.1.0.dist-info/RECORD
