Metadata-Version: 2.4
Name: nmdown
Version: 0.1.0
Summary: A terminal-based markdown editor using curses
Home-page: https://github.com/bearenbey/nmdown
Author: Eren Öğrül
Author-email: termapp@pm.me
Classifier: Programming Language :: Python :: 3
Classifier: Environment :: Console
Classifier: License :: OSI Approved :: MIT License
Classifier: Operating System :: Unix
Requires-Python: >=3.7
Dynamic: author
Dynamic: author-email
Dynamic: classifier
Dynamic: description
Dynamic: description-content-type
Dynamic: home-page
Dynamic: requires-python
Dynamic: summary
